eboekhoudennl_api/__init__.py
eboekhoudennl_api/eboek.py
eboekhoudennl_api-0.0.4.dist-info/LICENSE
eboekhoudennl_api-0.0.4.dist-info/METADATA
eboekhoudennl_api-0.0.4.dist-info/WHEEL
eboekhoudennl_api-0.0.4.dist-info/top_level.txt
eboekhoudennl_api-0.0.4.dist-info/RECORD
