Metadata-Version: 2.1
Name: eboekhoudennl-api
Version: 0.0.4
Summary: e-boekhouden api made easy
Author-email: RAYLAN <info@raylan.nl>
License: MIT License        
Project-URL: Home, https://github.com/raylanconsulting/eboekhouden
Classifier: License :: OSI Approved :: MIT License
Requires-Python: >=3.7
License-File: LICENSE
Requires-Dist: zeep
